[
 {
  "docstatus": 0,
  "doctype": "Workflow",
  "document_type": "Supplier",
  "is_active": 1,
  "modified": "2026-01-19 16:24:22.161350",
  "name": "Supplier Onboarding Workflow",
  "override_status": 0,
  "send_email_alert": 0,
  "states": [
   {
    "allow_edit": "Purchase Manager",
    "avoid_status_override": 0,
    "doc_status": "0",
    "is_optional_state": 0,
    "message": null,
    "next_action_email_template": null,
    "parent": "Supplier Onboarding Workflow",
    "parentfield": "states",
    "parenttype": "Workflow",
    "send_email": 1,
    "state": "Pending Purchase Engineer Approvel",
    "update_field": "disabled",
    "update_value": "1",
    "workflow_builder_id": null
   },
   {
    "allow_edit": "Sourcing Manager",
    "avoid_status_override": 0,
    "doc_status": "0",
    "is_optional_state": 0,
    "message": null,
    "next_action_email_template": null,
    "parent": "Supplier Onboarding Workflow",
    "parentfield": "states",
    "parenttype": "Workflow",
    "send_email": 1,
    "state": "Pending Sourcing Manager Approvel",
    "update_field": "disabled",
    "update_value": "1",
    "workflow_builder_id": null
   },
   {
    "allow_edit": "Senior Sourcing Manager",
    "avoid_status_override": 0,
    "doc_status": "0",
    "is_optional_state": 0,
    "message": null,
    "next_action_email_template": null,
    "parent": "Supplier Onboarding Workflow",
    "parentfield": "states",
    "parenttype": "Workflow",
    "send_email": 1,
    "state": "Pending Senior Sourcing Manager Approval",
    "update_field": "disabled",
    "update_value": "1",
    "workflow_builder_id": null
   },
   {
    "allow_edit": "Senior Sourcing Manager",
    "avoid_status_override": 0,
    "doc_status": "0",
    "is_optional_state": 0,
    "message": null,
    "next_action_email_template": null,
    "parent": "Supplier Onboarding Workflow",
    "parentfield": "states",
    "parenttype": "Workflow",
    "send_email": 1,
    "state": "Approved",
    "update_field": "disabled",
    "update_value": "0",
    "workflow_builder_id": null
   }
  ],
  "transitions": [
   {
    "action": "Approve",
    "allow_self_approval": 1,
    "allowed": "Purchase Manager",
    "condition": null,
    "next_state": "Pending Sourcing Manager Approvel",
    "parent": "Supplier Onboarding Workflow",
    "parentfield": "transitions",
    "parenttype": "Workflow",
    "send_email_to_creator": 0,
    "state": "Pending Purchase Engineer Approvel",
    "workflow_builder_id": null
   },
   {
    "action": "Approve",
    "allow_self_approval": 1,
    "allowed": "Sourcing Manager",
    "condition": null,
    "next_state": "Pending Senior Sourcing Manager Approval",
    "parent": "Supplier Onboarding Workflow",
    "parentfield": "transitions",
    "parenttype": "Workflow",
    "send_email_to_creator": 0,
    "state": "Pending Sourcing Manager Approvel",
    "workflow_builder_id": null
   },
   {
    "action": "Approve",
    "allow_self_approval": 1,
    "allowed": "Senior Sourcing Manager",
    "condition": null,
    "next_state": "Approved",
    "parent": "Supplier Onboarding Workflow",
    "parentfield": "transitions",
    "parenttype": "Workflow",
    "send_email_to_creator": 0,
    "state": "Pending Senior Sourcing Manager Approval",
    "workflow_builder_id": null
   }
  ],
  "workflow_data": null,
  "workflow_name": "Supplier Onboarding Workflow",
  "workflow_state_field": "workflow_state"
 },
 {
  "docstatus": 0,
  "doctype": "Workflow",
  "document_type": "Quality Inspection",
  "is_active": 1,
  "modified": "2026-02-26 09:38:30.644093",
  "name": "Quality Inspection Workflow",
  "override_status": 0,
  "send_email_alert": 0,
  "states": [
   {
    "allow_edit": "Quality Manager",
    "avoid_status_override": 0,
    "doc_status": "0",
    "is_optional_state": 0,
    "message": null,
    "next_action_email_template": null,
    "parent": "Quality Inspection Workflow",
    "parentfield": "states",
    "parenttype": "Workflow",
    "send_email": 1,
    "state": "Pending For Quality Inspection",
    "update_field": null,
    "update_value": null,
    "workflow_builder_id": null
   },
   {
    "allow_edit": "Quality Manager",
    "avoid_status_override": 0,
    "doc_status": "1",
    "is_optional_state": 0,
    "message": null,
    "next_action_email_template": null,
    "parent": "Quality Inspection Workflow",
    "parentfield": "states",
    "parenttype": "Workflow",
    "send_email": 1,
    "state": "Quality Inspection Completed",
    "update_field": null,
    "update_value": null,
    "workflow_builder_id": null
   },
   {
    "allow_edit": "Quality Manager",
    "avoid_status_override": 0,
    "doc_status": "2",
    "is_optional_state": 0,
    "message": null,
    "next_action_email_template": null,
    "parent": "Quality Inspection Workflow",
    "parentfield": "states",
    "parenttype": "Workflow",
    "send_email": 1,
    "state": "Cancelled",
    "update_field": null,
    "update_value": null,
    "workflow_builder_id": null
   }
  ],
  "transitions": [
   {
    "action": "Approve",
    "allow_self_approval": 1,
    "allowed": "Quality Manager",
    "condition": null,
    "next_state": "Quality Inspection Completed",
    "parent": "Quality Inspection Workflow",
    "parentfield": "transitions",
    "parenttype": "Workflow",
    "send_email_to_creator": 0,
    "state": "Pending For Quality Inspection",
    "workflow_builder_id": null
   },
   {
    "action": "Cancel",
    "allow_self_approval": 1,
    "allowed": "Quality Manager",
    "condition": null,
    "next_state": "Cancelled",
    "parent": "Quality Inspection Workflow",
    "parentfield": "transitions",
    "parenttype": "Workflow",
    "send_email_to_creator": 0,
    "state": "Quality Inspection Completed",
    "workflow_builder_id": null
   }
  ],
  "workflow_data": null,
  "workflow_name": "Quality Inspection Workflow",
  "workflow_state_field": "workflow_state"
 },
 {
  "docstatus": 0,
  "doctype": "Workflow",
  "document_type": "Purchase Receipt",
  "is_active": 0,
  "modified": "2026-02-26 12:24:45.176149",
  "name": "Quanlity Inspection at Purchase Receipt",
  "override_status": 0,
  "send_email_alert": 0,
  "states": [
   {
    "allow_edit": "Purchase User",
    "avoid_status_override": 1,
    "doc_status": "0",
    "is_optional_state": 0,
    "message": null,
    "next_action_email_template": null,
    "parent": "Quanlity Inspection at Purchase Receipt",
    "parentfield": "states",
    "parenttype": "Workflow",
    "send_email": 1,
    "state": "Draft",
    "update_field": "",
    "update_value": null,
    "workflow_builder_id": null
   },
   {
    "allow_edit": "Purchase User",
    "avoid_status_override": 0,
    "doc_status": "0",
    "is_optional_state": 0,
    "message": null,
    "next_action_email_template": null,
    "parent": "Quanlity Inspection at Purchase Receipt",
    "parentfield": "states",
    "parenttype": "Workflow",
    "send_email": 1,
    "state": "Pending For Quality Inspection",
    "update_field": "status",
    "update_value": "Pending For Quality Inspection",
    "workflow_builder_id": null
   },
   {
    "allow_edit": "Purchase Manager",
    "avoid_status_override": 1,
    "doc_status": "1",
    "is_optional_state": 0,
    "message": null,
    "next_action_email_template": null,
    "parent": "Quanlity Inspection at Purchase Receipt",
    "parentfield": "states",
    "parenttype": "Workflow",
    "send_email": 1,
    "state": "Approved",
    "update_field": null,
    "update_value": null,
    "workflow_builder_id": null
   },
   {
    "allow_edit": "Purchase Manager",
    "avoid_status_override": 1,
    "doc_status": "2",
    "is_optional_state": 0,
    "message": null,
    "next_action_email_template": null,
    "parent": "Quanlity Inspection at Purchase Receipt",
    "parentfield": "states",
    "parenttype": "Workflow",
    "send_email": 1,
    "state": "Cancelled",
    "update_field": null,
    "update_value": null,
    "workflow_builder_id": null
   }
  ],
  "transitions": [
   {
    "action": "Quality Inspection",
    "allow_self_approval": 0,
    "allowed": "Purchase User",
    "condition": null,
    "next_state": "Pending For Quality Inspection",
    "parent": "Quanlity Inspection at Purchase Receipt",
    "parentfield": "transitions",
    "parenttype": "Workflow",
    "send_email_to_creator": 0,
    "state": "Draft",
    "workflow_builder_id": null
   },
   {
    "action": "Approve",
    "allow_self_approval": 1,
    "allowed": "Purchase Manager",
    "condition": null,
    "next_state": "Approved",
    "parent": "Quanlity Inspection at Purchase Receipt",
    "parentfield": "transitions",
    "parenttype": "Workflow",
    "send_email_to_creator": 0,
    "state": "Draft",
    "workflow_builder_id": null
   },
   {
    "action": "Approve",
    "allow_self_approval": 1,
    "allowed": "Purchase Manager",
    "condition": null,
    "next_state": "Approved",
    "parent": "Quanlity Inspection at Purchase Receipt",
    "parentfield": "transitions",
    "parenttype": "Workflow",
    "send_email_to_creator": 0,
    "state": "Pending For Quality Inspection",
    "workflow_builder_id": null
   },
   {
    "action": "Cancel",
    "allow_self_approval": 1,
    "allowed": "Purchase Manager",
    "condition": null,
    "next_state": "Cancelled",
    "parent": "Quanlity Inspection at Purchase Receipt",
    "parentfield": "transitions",
    "parenttype": "Workflow",
    "send_email_to_creator": 0,
    "state": "Approved",
    "workflow_builder_id": null
   }
  ],
  "workflow_data": null,
  "workflow_name": "Quanlity Inspection at Purchase Receipt",
  "workflow_state_field": "workflow_state"
 }
]